{
  "corp_code": "005380",
  "corp_name": "현대자동차",
  "industry": "자동차",
  "report_year": 2024,
  "source": "DART 사업보고서 + 지속가능성보고서 2024 (공개 데이터 발췌)",
  "financials": {
    "revenue_krw": 162664000000000,
    "operating_profit_krw": 15127000000000
  },
  "kesg_data": {
    "P-1-1": {"value": "지속가능성보고서 + DART 사업보고서 + 홈페이지", "unit": "-", "note": "GRI Standards·TCFD 기준 공시"},
    "P-1-2": {"value": "연 1회", "unit": "-", "note": "매년 4월 발간 (전년도 실적 기준)"},
    "P-1-3": {"value": "연결 기준 (현대차그룹 주요 법인)", "unit": "-", "note": "국내외 완성차 생산법인 포함"},
    "P-2-1": {"value": "중대성 평가 12개 핵심이슈 선정", "unit": "-", "note": "이해관계자·사업 영향도 분석 기반, KPI 공시"},
    "P-3-1": {"value": "한국경영인증원(KMR) 제3자 검증", "unit": "-", "note": "ISO 14064-3 온실가스 검증"},
    "E-1-1": {"value": "2045 탄소중립 (밸류체인 포함)", "unit": "-", "note": "전 사업장 RE100, 전기차 전환 로드맵 수립"},
    "E-1-2": {"value": "그룹 환경안전본부 + 사업장별 환경위원회", "unit": "-", "note": "C레벨 ESG위원회 분기 보고"},
    "E-2-1": {"value": 8900000, "unit": "ton", "note": "철강·비철금속·플라스틱 등 원부자재 총 사용량"},
    "E-3-1": {"value": 1620000, "unit": "tCO2eq", "note": "Scope1+2 글로벌"},
    "E-3-2": {"value": 78500000, "unit": "tCO2eq", "note": "Scope3 (사용단계 포함)"},
    "E-3-3": {"value": "KMR 제3자 검증", "unit": "-", "note": "ISO 14064-3"},
    "E-4-1": {"value": 26.8, "unit": "TJ", "note": "연간 에너지 사용량 (글로벌)"},
    "E-4-2": {"value": 12.4, "unit": "%", "note": "재생에너지 사용 비율"},
    "E-5-1": {"value": 23500000, "unit": "ton", "note": "연간 취수량"},
    "E-5-2": {"value": 14.2, "unit": "%", "note": "재사용 용수 비율"},
    "E-6-1": {"value": 524000, "unit": "ton", "note": "폐기물 배출량"},
    "E-6-2": {"value": 93.2, "unit": "%", "note": "폐기물 재활용 비율"},
    "E-7-1": {"value": 4230, "unit": "kg", "note": "VOCs·NOx 등 대기오염물질 배출량"},
    "E-7-2": {"value": 1150, "unit": "kg", "note": "COD·SS 등 수질오염물질 배출량"},
    "E-8-1": {"value": 1, "unit": "건", "note": "경미한 환경 법규 위반 1건, 과징금 800만 원"},
    "S-1-1": {"value": "2030 사회적 책임 이행 목표 수립", "unit": "-", "note": "안전·인권·협력사 상생 중심 목표 체계"},
    "S-2-1": {"value": 9500, "unit": "명", "note": "국내외 신규 채용 (정규직 기준)"},
    "S-2-2": {"value": 97.3, "unit": "%", "note": "국내 정규직 비율"},
    "S-2-3": {"value": 1.1, "unit": "%", "note": "자발적 이직률"},
    "S-2-4": {"value": 1620000, "unit": "원/인", "note": "1인당 연간 교육훈련비"},
    "S-2-6": {"value": "전국금속노동조합 현대차지부 등 복수노조", "unit": "-", "note": "단체교섭권 및 결사의 자유 보장"},
    "S-3-1": {"value": 8.4, "unit": "%", "note": "여성 구성원 비율"},
    "S-3-3": {"value": 2.3, "unit": "%", "note": "장애인 고용률"},
    "S-4-1": {"value": "안전보건 전담 조직 및 중대재해 예방 체계 운영", "unit": "-", "note": "중대재해처벌법 대응 안전보건경영시스템 구축"},
    "S-4-2": {"value": 0.44, "unit": "%", "note": "재해율"},
    "S-5-1": {"value": "인권 경영 선언 및 인권 정책 공시", "unit": "-", "note": "UN 기업과 인권 이행 원칙 준수"},
    "S-6-1": {"value": "협력사 ESG 평가 및 컨설팅 지원", "unit": "-", "note": "1·2차 협력사 ESG 역량 진단 실시"},
    "S-6-2": {"value": "협력사 금융·기술 지원 프로그램 운영", "unit": "-", "note": "상생협력 펀드 5,000억 원 조성"},
    "S-7-1": {"value": "정몽구재단 통한 전략적 사회공헌", "unit": "-", "note": "미래세대 교육·환경 분야 CSR 집중"},
    "S-8-2": {"value": 0, "unit": "건", "note": "중대 개인정보 침해 건수"},
    "G-1-1": {"value": "ESG 안건 연 3회 이상 이사회 상정", "unit": "-", "note": "지속가능경영위원회 분기 보고"},
    "G-1-2": {"value": 66.7, "unit": "%", "note": "사외이사 비율 (8/12)"},
    "G-1-3": {"value": "대표이사·이사회 의장 분리", "unit": "-", "note": "사외이사 의장 선임으로 독립성 확보"},
    "G-1-4": {"value": 16.7, "unit": "%", "note": "여성 이사 비율 (2/12)"},
    "G-2-1": {"value": 96.5, "unit": "%", "note": "이사회 출석률"},
    "G-2-3": {"value": "2024년 이사회 10회 개최, 72개 안건 심의", "unit": "-", "note": "주요 안건: 중장기 전략, 전동화 투자, ESG"},
    "G-3-1": {"value": "주주총회 개최 35일 전 공고", "unit": "-", "note": "전자투표 시스템 도입"},
    "G-3-4": {"value": 25.2, "unit": "%", "note": "배당 성향"},
    "G-4-1": {"value": "윤리준법경영 위반 사항 연간 공시", "unit": "-", "note": "신고 채널 운영, 처리 결과 공개"},
    "G-5-1": {"value": "감사위원회 + 내부감사실 운영", "unit": "-", "note": "내부감사실 독립 운영 (CEO 직속)"},
    "G-5-2": {"value": "감사위원 중 회계·재무 전문가 2인", "unit": "-", "note": "공인회계사 자격 보유 위원 포함"}
  },
  "raw_text_snippets": [
    "현대자동차는 2045년 탄소중립 달성을 목표로 전 사업장 재생에너지 100% 전환을 추진하고 있다.",
    "2024년 글로벌 재생에너지 비율은 12.4%이며, 유럽 사업장은 2030년까지 RE100 달성 예정이다.",
    "글로벌 Scope 1+2 배출량은 162만 tCO2eq 로 집계되었다.",
    "전기차 판매 비중 확대를 통해 Scope3 배출량 감축을 추진 중이다.",
    "이사회 사외이사 비율은 66.7%로 글로벌 모범 수준이다.",
    "중대재해 예방을 위해 안전보건 전담 조직을 운영하고 있다.",
    "지속가능성보고서는 GRI Standards 및 TCFD 기준으로 매년 4월 발간한다.",
    "1인당 교육훈련비는 162만 원이며, 협력사 ESG 역량 진단 결과를 기반으로 맞춤형 컨설팅을 제공하였다.",
    "상생협력 펀드 5,000억 원을 조성하여 1·2차 협력사에 저금리 금융 지원을 실시하였다.",
    "안전보건 전담 조직을 중심으로 중대재해처벌법 대응 체계를 구축하였으며, 재해율은 0.44%이다.",
    "이사회는 2024년 총 10회 개최되었으며, 전동화 전략 및 ESG 중장기 목표를 포함한 72개 안건을 심의하였다.",
    "대기오염물질 배출량은 4,230kg, 수질오염물질 배출량은 1,150kg으로 전년 대비 각각 5.2%, 3.8% 감소하였다."
  ]
}
